tests/__init__.py
tests/test_cliente.py
tests/test_conta.py
tests/test_transacoes.py
tunes_sys_bank-0.0.1.dist-info/licenses/LICENSE
tunes_sys_bank-0.0.1.dist-info/METADATA
tunes_sys_bank-0.0.1.dist-info/WHEEL
tunes_sys_bank-0.0.1.dist-info/top_level.txt
tunes_sys_bank-0.0.1.dist-info/RECORD
