Metadata-Version: 2.4
Name: tunes-sys-bank
Version: 0.0.1
Summary: Bank System package with basic operations
Home-page: https://github.com/antonyreis/bank-system
Author: Antony Matheus
Author-email: tonyto.matheus@gmail.com
Requires-Python: >=3.10
License-File: LICENSE
Dynamic: author
Dynamic: author-email
Dynamic: description
Dynamic: description-content-type
Dynamic: home-page
Dynamic: license-file
Dynamic: requires-python
Dynamic: summary
